.gitattributes
.gitignore
.gitlab-ci.yml
LICENSE-APACHE
LICENSE-MIT
Makefile
README.md
pyproject.toml
requirements-dev.txt
docs/changelog.rst
docs/conf.py
docs/deployment.rst
docs/icon.svg
docs/index.rst
docs/openrpc.rst
docs/quickstart.rst
docs/reference.rst
docs/changelog/v1.x.x/index.rst
docs/changelog/v1.x.x/v1.0.0.rst
docs/changelog/v1.x.x/v1.0.1.rst
docs/changelog/v1.x.x/v1.0.2.rst
docs/changelog/v1.x.x/v1.0.3.rst
docs/changelog/v1.x.x/v1.0.4.rst
docs/changelog/v1.x.x/v1.1.0.rst
docs/changelog/v2.x.x/index.rst
docs/changelog/v2.x.x/v2.0.0.rst
docs/changelog/v2.x.x/v2.0.1.rst
docs/changelog/v2.x.x/v2.0.2.rst
docs/changelog/v2.x.x/v2.1.0.rst
docs/changelog/v2.x.x/v2.2.0.rst
docs/changelog/v2.x.x/v2.2.1.rst
docs/changelog/v2.x.x/v2.2.2.rst
docs/changelog/v2.x.x/v2.2.3.rst
docs/changelog/v2.x.x/v2.3.0.rst
docs/changelog/v2.x.x/v2.4.0.rst
docs/changelog/v2.x.x/v2.4.1.rst
docs/changelog/v2.x.x/v2.4.2.rst
docs/changelog/v2.x.x/v2.4.3.rst
docs/changelog/v2.x.x/v2.4.4.rst
docs/changelog/v2.x.x/v2.4.5.rst
docs/changelog/v2.x.x/v2.4.6.rst
docs/changelog/v2.x.x/v2.4.7.rst
docs/changelog/v2.x.x/v2.4.8.rst
docs/changelog/v2.x.x/v2.4.9.rst
docs/changelog/v2.x.x/v2.5.0.rst
docs/changelog/v2.x.x/v2.5.1.rst
docs/changelog/v3.x.x/index.rst
docs/changelog/v3.x.x/v3.0.0.rst
docs/changelog/v3.x.x/v3.0.1.rst
docs/changelog/v3.x.x/v3.0.10.rst
docs/changelog/v3.x.x/v3.0.11.rst
docs/changelog/v3.x.x/v3.0.12.rst
docs/changelog/v3.x.x/v3.0.13.rst
docs/changelog/v3.x.x/v3.0.2.rst
docs/changelog/v3.x.x/v3.0.3.rst
docs/changelog/v3.x.x/v3.0.4.rst
docs/changelog/v3.x.x/v3.0.5.rst
docs/changelog/v3.x.x/v3.0.6.rst
docs/changelog/v3.x.x/v3.0.7.rst
docs/changelog/v3.x.x/v3.0.8.rst
docs/changelog/v3.x.x/v3.0.9.rst
docs/changelog/v3.x.x/v3.1.0.rst
docs/changelog/v3.x.x/v3.1.1.rst
docs/changelog/v3.x.x/v3.1.2.rst
docs/changelog/v3.x.x/v3.1.3.rst
docs/changelog/v3.x.x/v3.2.0.rst
docs/changelog/v3.x.x/v3.2.1.rst
docs/changelog/v3.x.x/v3.2.2.rst
docs/changelog/v3.x.x/v3.2.3.rst
src/jsonrpc_py.egg-info/PKG-INFO
src/jsonrpc_py.egg-info/SOURCES.txt
src/jsonrpc_py.egg-info/dependency_links.txt
src/jsonrpc_py.egg-info/requires.txt
src/jsonrpc_py.egg-info/top_level.txt
