Metadata-Version: 2.1
Name: jsonrpc-py
Version: 5.5.1
Summary: Pure zero-dependency JSON-RPC 2.0 and OpenRPC implementation
Author-email: Andrew Malchuk <andrew.malchuk@yandex.ru>
Maintainer-email: JSON-RPC Development Group <dev@jsonrpc.ru>
License: Apache-2.0 OR MIT
Project-URL: Homepage, https://docs.jsonrpc.ru
Project-URL: Source Code, https://gitlab.com/jsonrpc/jsonrpc-py
Project-URL: Documentation, https://docs.jsonrpc.ru
Project-URL: Change Log, https://docs.jsonrpc.ru/changelog.html
Keywords: jsonrpc,openrpc,asgi
Classifier: Development Status :: 5 - Production/Stable
Classifier: Environment :: Web Environment
Classifier: Framework :: AsyncIO
Classifier: Intended Audience :: Developers
Classifier: License :: OSI Approved :: Apache Software License
Classifier: License :: OSI Approved :: MIT License
Classifier: Operating System :: OS Independent
Classifier: Programming Language :: Python
Classifier: Programming Language :: Python :: 3
Classifier: Programming Language :: Python :: 3 :: Only
Classifier: Programming Language :: Python :: 3.12
Classifier: Programming Language :: Python :: 3.13
Classifier: Programming Language :: Python :: 3.14
Classifier: Programming Language :: Python :: Implementation :: CPython
Classifier: Topic :: Internet :: WWW/HTTP
Classifier: Topic :: Internet :: WWW/HTTP :: Dynamic Content
Classifier: Topic :: Software Development :: Libraries :: Application Frameworks
Classifier: Topic :: Software Development :: Libraries :: Python Modules
Classifier: Typing :: Typed
Requires-Python: >=3.12
License-File: LICENSE-APACHE
License-File: LICENSE-MIT
Provides-Extra: ujson
Requires-Dist: ujson<6.0,>=5.10; extra == "ujson"
